DynOpt/__init__.py
DynOpt/dyno.py
DynOpt-0.2.3.dist-info/LICENSE
DynOpt-0.2.3.dist-info/METADATA
DynOpt-0.2.3.dist-info/WHEEL
DynOpt-0.2.3.dist-info/top_level.txt
DynOpt-0.2.3.dist-info/RECORD
