Metadata-Version: 2.2
Name: DynOpt
Version: 0.2.3
Summary: Dynamic optimization toolbox for flow chemistry
Home-page: https://github.com/fflorit/DynOpt
Author: Federico Florit
Author-email: Federico Florit <federico.florit@gmail.com>
License: BSD 3-Clause License
Project-URL: Homepage, https://github.com/fflorit/DynOpt
Platform: any
Classifier: Programming Language :: Python :: 3
Classifier: License :: OSI Approved :: BSD License
Classifier: Operating System :: OS Independent
Requires-Python: >=3.6
License-File: LICENSE
Requires-Dist: numpy>=1.19.5
Requires-Dist: pandas>=1.1.5
Requires-Dist: scipy>=1.7.3
Requires-Dist: scikit-learn>=0.24.2
Requires-Dist: matplotlib>=3.3.4
